{"metadata":{},"options":{"compact":false,"sourceMaps":true,"ast":true,"babelrc":false,"configFile":false,"parserOpts":{"sourceType":"module","sourceFileName":"/Users/Florian/dev/epotek/microservices/backend/imports/core/api/borrowers/borrowers.js","plugins":["*","flow","jsx","asyncGenerators","bigInt","classPrivateMethods","classPrivateProperties","classProperties","doExpressions","dynamicImport","exportDefaultFrom","exportExtensions","exportNamespaceFrom","functionBind","functionSent","importMeta","nullishCoalescingOperator","numericSeparator","objectRestSpread","optionalCatchBinding","optionalChaining",["pipelineOperator",{"proposal":"minimal"}],"throwExpressions","classProperties","classPrivateProperties",["flow",{}],"jsx",["flow",{}],["flow",{}],"objectRestSpread","objectRestSpread","dynamicImport","asyncGenerators","classProperties","classPrivateProperties"],"allowImportExportEverywhere":true,"allowReturnOutsideFunction":true,"strictMode":false},"caller":{"name":"meteor","arch":"os.osx.x86_64"},"sourceFileName":"imports/core/api/borrowers/borrowers.js","filename":"/Users/Florian/dev/epotek/microservices/backend/imports/core/api/borrowers/borrowers.js","inputSourceMap":{"version":3,"sources":["imports/core/api/borrowers/borrowers.js"],"names":["Mongo","BORROWERS_COLLECTION","BorrowerSchema","Borrowers","Collection","deny","insert","update","remove","allow","attachSchema"],"mappings":"AAAA,SAASA,KAAT,QAAsB,cAAtB;AACA,SAASC,oBAAT;AACA,OAAOC,cAAP;AAEA,MAAMC,SAAS,GAAG,IAAIH,KAAK,CAACI,UAAV,CAAqBH,oBAArB,CAAlB,C,CAEA;;AACAE,SAAS,CAACE,IAAV,CAAe;AACbC,EAAAA,MAAM,EAAE,MAAM,IADD;AAEbC,EAAAA,MAAM,EAAE,MAAM,IAFD;AAGbC,EAAAA,MAAM,EAAE,MAAM;AAHD,CAAf;AAMAL,SAAS,CAACM,KAAV,CAAgB;AACdH,EAAAA,MAAM,EAAE,MAAM,KADA;AAEdC,EAAAA,MAAM,EAAE,MAAM,KAFA;AAGdC,EAAAA,MAAM,EAAE,MAAM;AAHA,CAAhB;AAMAL,SAAS,CAACO,YAAV,CAAuBR,cAAvB;AACA,eAAeC,SAAf","sourcesContent":["import { Mongo } from 'meteor/mongo';\nimport { BORROWERS_COLLECTION } from './borrowerConstants';\nimport BorrowerSchema from './schemas/BorrowerSchema';\n\nconst Borrowers = new Mongo.Collection(BORROWERS_COLLECTION);\n\n// Prevent all client side modifications of mongoDB\nBorrowers.deny({\n  insert: () => true,\n  update: () => true,\n  remove: () => true,\n});\n\nBorrowers.allow({\n  insert: () => false,\n  update: () => false,\n  remove: () => false,\n});\n\nBorrowers.attachSchema(BorrowerSchema);\nexport default Borrowers;\n"]},"passPerPreset":false,"envName":"development","cwd":"/Users/Florian/dev/epotek/microservices/backend","root":"/Users/Florian/dev/epotek/microservices/backend","plugins":[{"key":"transform-flow-strip-types","visitor":{"_exploded":{},"_verified":{},"Program":{"enter":[null]},"ImportDeclaration":{"enter":[null,null]},"ClassProperty":{"enter":[null]},"ClassPrivateProperty":{"enter":[null]},"AssignmentPattern":{"enter":[null]},"TypeCastExpression":{"enter":[null,null]},"CallExpression":{"enter":[null]},"OptionalCallExpression":{"enter":[null]},"NewExpression":{"enter":[null]},"ImportSpecifier":{"enter":[null]},"ClassDeclaration":{"enter":[null]},"ClassExpression":{"enter":[null]},"FunctionDeclaration":{"enter":[null]},"FunctionExpression":{"enter":[null]},"ObjectMethod":{"enter":[null]},"ArrowFunctionExpression":{"enter":[null]},"ClassMethod":{"enter":[null]},"ClassPrivateMethod":{"enter":[null]},"AnyTypeAnnotation":{"enter":[null]},"ArrayTypeAnnotation":{"enter":[null]},"BooleanTypeAnnotation":{"enter":[null]},"BooleanLiteralTypeAnnotation":{"enter":[null]},"NullLiteralTypeAnnotation":{"enter":[null]},"ClassImplements":{"enter":[null]},"DeclareClass":{"enter":[null]},"DeclareFunction":{"enter":[null]},"DeclareInterface":{"enter":[null]},"DeclareModule":{"enter":[null]},"DeclareModuleExports":{"enter":[null]},"DeclareTypeAlias":{"enter":[null]},"DeclareOpaqueType":{"enter":[null]},"DeclareVariable":{"enter":[null]},"DeclareExportDeclaration":{"enter":[null]},"DeclareExportAllDeclaration":{"enter":[null]},"DeclaredPredicate":{"enter":[null]},"ExistsTypeAnnotation":{"enter":[null]},"FunctionTypeAnnotation":{"enter":[null]},"FunctionTypeParam":{"enter":[null]},"GenericTypeAnnotation":{"enter":[null]},"InferredPredicate":{"enter":[null]},"InterfaceExtends":{"enter":[null]},"InterfaceDeclaration":{"enter":[null]},"InterfaceTypeAnnotation":{"enter":[null]},"IntersectionTypeAnnotation":{"enter":[null]},"MixedTypeAnnotation":{"enter":[null]},"EmptyTypeAnnotation":{"enter":[null]},"NullableTypeAnnotation":{"enter":[null]},"NumberLiteralTypeAnnotation":{"enter":[null]},"NumberTypeAnnotation":{"enter":[null]},"ObjectTypeAnnotation":{"enter":[null]},"ObjectTypeInternalSlot":{"enter":[null]},"ObjectTypeCallProperty":{"enter":[null]},"ObjectTypeIndexer":{"enter":[null]},"ObjectTypeProperty":{"enter":[null]},"ObjectTypeSpreadProperty":{"enter":[null]},"OpaqueType":{"enter":[null]},"QualifiedTypeIdentifier":{"enter":[null]},"StringLiteralTypeAnnotation":{"enter":[null]},"StringTypeAnnotation":{"enter":[null]},"ThisTypeAnnotation":{"enter":[null]},"TupleTypeAnnotation":{"enter":[null]},"TypeofTypeAnnotation":{"enter":[null]},"TypeAlias":{"enter":[null]},"TypeAnnotation":{"enter":[null]},"TypeParameter":{"enter":[null]},"TypeParameterDeclaration":{"enter":[null]},"TypeParameterInstantiation":{"enter":[null]},"UnionTypeAnnotation":{"enter":[null]},"Variance":{"enter":[null]},"VoidTypeAnnotation":{"enter":[null]},"ExportAllDeclaration":{"enter":[null]},"ExportDefaultDeclaration":{"enter":[null]},"ExportNamedDeclaration":{"enter":[null]}},"options":{}},{"key":"transform-react-jsx","visitor":{"_exploded":{},"_verified":{},"JSXNamespacedName":{"enter":[null]},"JSXSpreadChild":{"enter":[null]},"JSXElement":{"exit":[null]},"JSXFragment":{"exit":[null]},"Program":{"enter":[null],"exit":[null]},"JSXAttribute":{"enter":[null]}},"options":{"pragma":"React.createElement","pragmaFrag":"React.Fragment","throwIfNamespace":true,"useBuiltIns":false}},{"key":"transform-react-display-name","visitor":{"ExportDefaultDeclaration":{"enter":[null]},"CallExpression":{"enter":[null]},"_exploded":true,"_verified":true},"options":{}},{"key":"base$0$0","visitor":{"Program":{"enter":[null]},"_exploded":true,"_verified":true},"options":{"generateLetDeclarations":true,"enforceStrictMode":false}},{"key":"syntax-flow","visitor":{"_exploded":true,"_verified":true},"options":{}},{"key":"transform-flow-strip-types","visitor":{"_exploded":{},"_verified":{},"Program":{"enter":[null]},"ImportDeclaration":{"enter":[null,null]},"ClassProperty":{"enter":[null]},"ClassPrivateProperty":{"enter":[null]},"AssignmentPattern":{"enter":[null]},"TypeCastExpression":{"enter":[null,null]},"CallExpression":{"enter":[null]},"OptionalCallExpression":{"enter":[null]},"NewExpression":{"enter":[null]},"ImportSpecifier":{"enter":[null]},"ClassDeclaration":{"enter":[null]},"ClassExpression":{"enter":[null]},"FunctionDeclaration":{"enter":[null]},"FunctionExpression":{"enter":[null]},"ObjectMethod":{"enter":[null]},"ArrowFunctionExpression":{"enter":[null]},"ClassMethod":{"enter":[null]},"ClassPrivateMethod":{"enter":[null]},"AnyTypeAnnotation":{"enter":[null]},"ArrayTypeAnnotation":{"enter":[null]},"BooleanTypeAnnotation":{"enter":[null]},"BooleanLiteralTypeAnnotation":{"enter":[null]},"NullLiteralTypeAnnotation":{"enter":[null]},"ClassImplements":{"enter":[null]},"DeclareClass":{"enter":[null]},"DeclareFunction":{"enter":[null]},"DeclareInterface":{"enter":[null]},"DeclareModule":{"enter":[null]},"DeclareModuleExports":{"enter":[null]},"DeclareTypeAlias":{"enter":[null]},"DeclareOpaqueType":{"enter":[null]},"DeclareVariable":{"enter":[null]},"DeclareExportDeclaration":{"enter":[null]},"DeclareExportAllDeclaration":{"enter":[null]},"DeclaredPredicate":{"enter":[null]},"ExistsTypeAnnotation":{"enter":[null]},"FunctionTypeAnnotation":{"enter":[null]},"FunctionTypeParam":{"enter":[null]},"GenericTypeAnnotation":{"enter":[null]},"InferredPredicate":{"enter":[null]},"InterfaceExtends":{"enter":[null]},"InterfaceDeclaration":{"enter":[null]},"InterfaceTypeAnnotation":{"enter":[null]},"IntersectionTypeAnnotation":{"enter":[null]},"MixedTypeAnnotation":{"enter":[null]},"EmptyTypeAnnotation":{"enter":[null]},"NullableTypeAnnotation":{"enter":[null]},"NumberLiteralTypeAnnotation":{"enter":[null]},"NumberTypeAnnotation":{"enter":[null]},"ObjectTypeAnnotation":{"enter":[null]},"ObjectTypeInternalSlot":{"enter":[null]},"ObjectTypeCallProperty":{"enter":[null]},"ObjectTypeIndexer":{"enter":[null]},"ObjectTypeProperty":{"enter":[null]},"ObjectTypeSpreadProperty":{"enter":[null]},"OpaqueType":{"enter":[null]},"QualifiedTypeIdentifier":{"enter":[null]},"StringLiteralTypeAnnotation":{"enter":[null]},"StringTypeAnnotation":{"enter":[null]},"ThisTypeAnnotation":{"enter":[null]},"TupleTypeAnnotation":{"enter":[null]},"TypeofTypeAnnotation":{"enter":[null]},"TypeAlias":{"enter":[null]},"TypeAnnotation":{"enter":[null]},"TypeParameter":{"enter":[null]},"TypeParameterDeclaration":{"enter":[null]},"TypeParameterInstantiation":{"enter":[null]},"UnionTypeAnnotation":{"enter":[null]},"Variance":{"enter":[null]},"VoidTypeAnnotation":{"enter":[null]},"ExportAllDeclaration":{"enter":[null]},"ExportDefaultDeclaration":{"enter":[null]},"ExportNamedDeclaration":{"enter":[null]}},"options":{}},{"key":"transform-runtime","visitor":{"CallExpression":{"enter":[null]},"BinaryExpression":{"enter":[null]},"MemberExpression":{"enter":[null],"exit":[null]},"_exploded":true,"_verified":true,"Identifier":{"enter":[null]},"JSXIdentifier":{"enter":[null]}},"options":{}},{"key":"syntax-object-rest-spread","visitor":{"_exploded":true,"_verified":true},"options":{}},{"key":"proposal-object-rest-spread","visitor":{"_exploded":{},"_verified":{},"VariableDeclarator":{"enter":[null]},"ExportNamedDeclaration":{"enter":[null]},"CatchClause":{"enter":[null]},"AssignmentExpression":{"enter":[null]},"ObjectExpression":{"enter":[null]},"FunctionDeclaration":{"enter":[null]},"FunctionExpression":{"enter":[null]},"ObjectMethod":{"enter":[null]},"ArrowFunctionExpression":{"enter":[null]},"ClassMethod":{"enter":[null]},"ClassPrivateMethod":{"enter":[null]},"ForInStatement":{"enter":[null]},"ForOfStatement":{"enter":[null]}},"options":{}},{"key":"transform-meteor-async-await","visitor":{"AwaitExpression":{"enter":[null]},"_exploded":true,"_verified":true,"FunctionDeclaration":{"exit":[null]},"FunctionExpression":{"exit":[null]},"ObjectMethod":{"exit":[null]},"ArrowFunctionExpression":{"exit":[null]},"ClassMethod":{"exit":[null]},"ClassPrivateMethod":{"exit":[null]}},"options":{"useNativeAsyncAwait":false}},{"key":"transform-meteor-dynamic-import","visitor":{"_exploded":{},"_verified":{},"CallExpression":{"enter":[null]}},"options":{}},{"key":"proposal-async-generator-functions","visitor":{"_exploded":{},"_verified":{},"Program":{"enter":[null]}},"options":{}},{"key":"transform-modules-commonjs","visitor":{"Program":{"exit":[null]},"_exploded":true,"_verified":true},"options":{"allowTopLevelThis":true,"strictMode":false,"loose":true}},{"key":"proposal-class-properties","visitor":{"PrivateName":{"enter":[null]},"ExportDefaultDeclaration":{"enter":[null]},"_exploded":true,"_verified":true,"ClassDeclaration":{"enter":[null]},"ClassExpression":{"enter":[null]}},"options":{"loose":true}}],"presets":[],"generatorOpts":{"filename":"/Users/Florian/dev/epotek/microservices/backend/imports/core/api/borrowers/borrowers.js","comments":true,"compact":false,"sourceMaps":true,"sourceFileName":"imports/core/api/borrowers/borrowers.js"}},"code":"let Mongo;\nmodule.link(\"meteor/mongo\", {\n  Mongo(v) {\n    Mongo = v;\n  }\n\n}, 0);\nlet BORROWERS_COLLECTION;\nmodule.link(\"./borrowerConstants\", {\n  BORROWERS_COLLECTION(v) {\n    BORROWERS_COLLECTION = v;\n  }\n\n}, 1);\nlet BorrowerSchema;\nmodule.link(\"./schemas/BorrowerSchema\", {\n  default(v) {\n    BorrowerSchema = v;\n  }\n\n}, 2);\nconst Borrowers = new Mongo.Collection(BORROWERS_COLLECTION); // Prevent all client side modifications of mongoDB\n\nBorrowers.deny({\n  insert: () => true,\n  update: () => true,\n  remove: () => true\n});\nBorrowers.allow({\n  insert: () => false,\n  update: () => false,\n  remove: () => false\n});\nBorrowers.attachSchema(BorrowerSchema);\nmodule.exportDefault(Borrowers);","map":{"version":3,"sources":["imports/core/api/borrowers/borrowers.js"],"names":["Borrowers","Mongo","insert","update","remove"],"mappings":"AAAA,IAAA,KAAA;AAAA,MAAA,CAAA,IAAA,CAAA,cAAA,EAAA;AAAA,EAAA,KAAA,CAAA,CAAA,EAAA;AAAA,IAAA,KAAA,GAAA,CAAA;AAAA;;AAAA,CAAA,EAAA,CAAA;AAAA,IAAA,oBAAA;AAAA,MAAA,CAAA,IAAA,CAAA,qBAAA,EAAA;AAAA,EAAA,oBAAA,CAAA,CAAA,EAAA;AAAA,IAAA,oBAAA,GAAA,CAAA;AAAA;;AAAA,CAAA,EAAA,CAAA;AAAA,IAAA,cAAA;AAAA,MAAA,CAAA,IAAA,CAAA,0BAAA,EAAA;AAAA,EAAA,OAAA,CAAA,CAAA,EAAA;AAAA,IAAA,cAAA,GAAA,CAAA;AAAA;;AAAA,CAAA,EAAA,CAAA;AAIA,MAAMA,SAAS,GAAG,IAAIC,KAAK,CAAT,UAAA,CAAlB,oBAAkB,CAAlB,C,CAEA;;AACAD,SAAS,CAATA,IAAAA,CAAe;AACbE,EAAAA,MAAM,EAAE,MADK,IAAA;AAEbC,EAAAA,MAAM,EAAE,MAFK,IAAA;AAGbC,EAAAA,MAAM,EAAE,MAAM;AAHD,CAAfJ;AAMAA,SAAS,CAATA,KAAAA,CAAgB;AACdE,EAAAA,MAAM,EAAE,MADM,KAAA;AAEdC,EAAAA,MAAM,EAAE,MAFM,KAAA;AAGdC,EAAAA,MAAM,EAAE,MAAM;AAHA,CAAhBJ;AAMAA,SAAS,CAATA,YAAAA,CAAAA,cAAAA;AAnBA,MAAA,CAAA,aAAA,CAoBA,SApBA","sourcesContent":["import { Mongo } from 'meteor/mongo';\nimport { BORROWERS_COLLECTION } from './borrowerConstants';\nimport BorrowerSchema from './schemas/BorrowerSchema';\n\nconst Borrowers = new Mongo.Collection(BORROWERS_COLLECTION);\n\n// Prevent all client side modifications of mongoDB\nBorrowers.deny({\n  insert: () => true,\n  update: () => true,\n  remove: () => true,\n});\n\nBorrowers.allow({\n  insert: () => false,\n  update: () => false,\n  remove: () => false,\n});\n\nBorrowers.attachSchema(BorrowerSchema);\nexport default Borrowers;\n"]},"sourceType":"script","hash":"e619c64f5beb98212c23a02220585f6799d01a52"}
