{
  "public": {
    "environment": "production",
    "features": {
      "LITE_VERSION": true,
      "NOT_PRODUCTION_READY": true
    },
    "analyticsSettings": {
      "Hotjar": {
        "app": {
          "hjid": "1310709"
        },
        "pro": {
          "hjid": "1310711"
        },
        "www": {
          "hjid": "1310643"
        }
      },
      "Segment": {
        "key": "G93hv64QSld1gnjzSlBWhQDFl44oyDmE"
      }
    },
    "google_maps_key": "AIzaSyCST4zOC76R4fBa2NazYDP3Nzv1xuottw4",
    "subdomains": {
      "admin": "https://admin.e-potek.ch",
      "app": "https://app.e-potek.ch",
      "pro": "https://pro.e-potek.ch",
      "www": "https://www.e-potek.ch",
      "backend": "https://backend.e-potek.ch"
    }
  },
  "mandrill": {
    "MANDRILL_LOGIN": "florian@e-potek.ch",
    "MANDRILL_API_KEY": "Bn4sTZ-Q9JqK-PyXACgJ_w",
    "MANDRILL_API_KEY_TEST": "pV16e1Ez1JD7CPqnZdkgZg"
  },
  "Monti": {
    "www": {
      "appId": "ec9rXiSyuwckHcLML",
      "appSecret": "0eab02c3-21d1-41d3-8af3-b9a8045a6f5d"
    },
    "admin": {
      "appId": "XvADC8QSa2ffEEWwL",
      "appSecret": "225bab95-5090-4ef0-9c91-3bdee8c980fa"
    },
    "app": {
      "appId": "7biJnXCK5H4KRZHXk",
      "appSecret": "64d55cf8-3be9-41fe-adeb-4b76825c9076"
    },
    "pro": {
      "appId": "qRFrSndRuuavPg64i",
      "appSecret": "e11cf37b-1ef8-4fc0-acce-f451f4c012ab"
    },
    "backend": {
      "appId": "3g7w3bTRF3PcNBSsr",
      "appSecret": "c98a4899-a226-4746-86c2-c6a02662c6d9"
    }
  },
  "storage": {
    "bucketName": "e-potek-production-files"
  },
  "exoscale": {
    "API_KEY": "EXOfaa01de0dd64ae217e1748c2",
    "SECRET_KEY": "QOMZaTbdybrigeFg2bTeNMcXAKXBebdJjkIAoYonyRU"
  },
  "redisOplog": {
    "redis": {
      "port": 45783,
      "host": "kubernetes-service-node.service.consul",
      "password": "Z524DK6IDGXOznCJtQZVpOadaiaK7a"
    },
    "retryIntervalMs": 10000,
    "mutationDefaults": {
      "optimistic": true,
      "pushToRedis": true
    },
    "debug": false,
    "overridePublishFunction": true
  },
  "DOC_RAPTOR_API_KEY": "GkjsAcqhD34P070MOF4I",
  "mixpanel": {
    "API_KEY": "032982c31f75296d6b55dd1fc320d010",
    "API_SECRET": "588391016d523645337c6c6e7e4d8506"
  },
  "PrerenderIO": {
    "token": "Aj24eX80LV6tWvKfc8rl"
  }
}
